odoo/addons/fieldservice_skill/README.rst
odoo/addons/fieldservice_skill/__init__.py
odoo/addons/fieldservice_skill/__manifest__.py
odoo/addons/fieldservice_skill/i18n/de.po
odoo/addons/fieldservice_skill/i18n/es.po
odoo/addons/fieldservice_skill/i18n/es_CL.po
odoo/addons/fieldservice_skill/i18n/fieldservice_skill.pot
odoo/addons/fieldservice_skill/i18n/pt_BR.po
odoo/addons/fieldservice_skill/models/__init__.py
odoo/addons/fieldservice_skill/models/fsm_category.py
odoo/addons/fieldservice_skill/models/fsm_order.py
odoo/addons/fieldservice_skill/models/fsm_person.py
odoo/addons/fieldservice_skill/models/fsm_person_skill.py
odoo/addons/fieldservice_skill/models/fsm_template.py
odoo/addons/fieldservice_skill/readme/CONFIGURE.rst
odoo/addons/fieldservice_skill/readme/CONTRIBUTORS.rst
odoo/addons/fieldservice_skill/readme/CREDITS.rst
odoo/addons/fieldservice_skill/readme/DESCRIPTION.rst
odoo/addons/fieldservice_skill/readme/INSTALL.rst
odoo/addons/fieldservice_skill/readme/ROADMAP.rst
odoo/addons/fieldservice_skill/readme/USAGE.rst
odoo/addons/fieldservice_skill/security/ir.model.access.csv
odoo/addons/fieldservice_skill/static/description/icon.png
odoo/addons/fieldservice_skill/static/description/index.html
odoo/addons/fieldservice_skill/views/fsm_category.xml
odoo/addons/fieldservice_skill/views/fsm_order.xml
odoo/addons/fieldservice_skill/views/fsm_person.xml
odoo/addons/fieldservice_skill/views/fsm_person_skill.xml
odoo/addons/fieldservice_skill/views/fsm_template.xml
odoo/addons/fieldservice_skill/views/hr_skill.xml
odoo12_addon_fieldservice_skill-12.0.1.1.0.dist-info/METADATA
odoo12_addon_fieldservice_skill-12.0.1.1.0.dist-info/WHEEL
odoo12_addon_fieldservice_skill-12.0.1.1.0.dist-info/top_level.txt
odoo12_addon_fieldservice_skill-12.0.1.1.0.dist-info/RECORD
